rcsb/__init__.py
rcsb/utils/__init__.py
rcsb/utils/io/CacheUtils.py
rcsb/utils/io/CryptUtils.py
rcsb/utils/io/ExecUtils.py
rcsb/utils/io/FastaUtil.py
rcsb/utils/io/FileUtil.py
rcsb/utils/io/HashableDict.py
rcsb/utils/io/IoUtil.py
rcsb/utils/io/MarshalUtil.py
rcsb/utils/io/ProcessStatusUtil.py
rcsb/utils/io/SftpUtil.py
rcsb/utils/io/SingletonClass.py
rcsb/utils/io/StashUtil.py
rcsb/utils/io/TimeUtil.py
rcsb/utils/io/UrlRequestUtil.py
rcsb/utils/io/__init__.py
rcsb/utils/io/decorators.py
rcsb.utils.io-0.84.dist-info/LICENSE
rcsb.utils.io-0.84.dist-info/METADATA
rcsb.utils.io-0.84.dist-info/WHEEL
rcsb.utils.io-0.84.dist-info/entry_points.txt
rcsb.utils.io-0.84.dist-info/top_level.txt
rcsb.utils.io-0.84.dist-info/RECORD
